autogen_oaiapi/__init__.py
autogen_oaiapi/app/__init__.py
autogen_oaiapi/app/exception_handlers.py
autogen_oaiapi/app/middleware.py
autogen_oaiapi/app/router.py
autogen_oaiapi/app/routes/__init__.py
autogen_oaiapi/app/routes/v1/chat.py
autogen_oaiapi/app/routes/v1/models.py
autogen_oaiapi/base/__init__.py
autogen_oaiapi/base/_key_manager.py
autogen_oaiapi/base/utils.py
autogen_oaiapi/base/types/__init__.py
autogen_oaiapi/base/types/_chat_message.py
autogen_oaiapi/base/types/_registry.py
autogen_oaiapi/base/types/_response_and_resquset.py
autogen_oaiapi/base/types/_session.py
autogen_oaiapi/config/__init__.py
autogen_oaiapi/config/settings.py
autogen_oaiapi/manager/__init__.py
autogen_oaiapi/manager/api_key/__init__.py
autogen_oaiapi/manager/api_key/_json_key_manager.py
autogen_oaiapi/manager/api_key/_memory_key_manager.py
autogen_oaiapi/manager/api_key/_non_key_manager.py
autogen_oaiapi/message/__init__.py
autogen_oaiapi/message/message_converter.py
autogen_oaiapi/message/response_builder.py
autogen_oaiapi/model/__init__.py
autogen_oaiapi/model/_model.py
autogen_oaiapi/server/__init__.py
autogen_oaiapi/server/core.py
autogen_oaiapi/session_manager/__init__.py
autogen_oaiapi/session_manager/base.py
autogen_oaiapi/session_manager/file.py
autogen_oaiapi/session_manager/memory.py
autogen_oaiapi-0.0.7.dist-info/licenses/LICENSE
autogen_oaiapi-0.0.7.dist-info/METADATA
autogen_oaiapi-0.0.7.dist-info/WHEEL
autogen_oaiapi-0.0.7.dist-info/top_level.txt
autogen_oaiapi-0.0.7.dist-info/RECORD
