Metadata-Version: 2.4
Name: autogen-oaiapi
Version: 0.0.7
Summary: An OpenAI-compatible API server for AutoGen.
Author-email: SongChiYoung <stchuck2008@gmail.com>
License: MIT
Project-URL: Homepage, https://github.com/SongChiYoung/autogen-oaiapi
Project-URL: Repository, https://github.com/SongChiYoung/autogen-oaiapi
Project-URL: Issues, https://github.com/SongChiYoung/autogen-oaiapi/issues
Keywords: autogen,openai,fastapi,llm,chat-completion
Classifier: Development Status :: 3 - Alpha
Classifier: License :: OSI Approved :: MIT License
Classifier: Programming Language :: Python :: 3
Classifier: Programming Language :: Python :: 3.10
Classifier: Programming Language :: Python :: 3.11
Classifier: Programming Language :: Python :: 3.12
Classifier: Framework :: FastAPI
Classifier: Intended Audience :: Developers
Classifier: Topic :: Software Development :: Libraries :: Application Frameworks
Requires-Python: >=3.10
License-File: LICENSE
Requires-Dist: fastapi>=0.95.0
Requires-Dist: uvicorn[standard]>=0.21.0
Requires-Dist: autogen-core>=0.5.1
Requires-Dist: autogen-ext>=0.5.1
Requires-Dist: autogen-ext[openai]>=0.5.1
Requires-Dist: autogen-agentchat>=0.5.1
Provides-Extra: dev
Requires-Dist: pytest; extra == "dev"
Requires-Dist: pytest-asyncio; extra == "dev"
Requires-Dist: pytest-cov; extra == "dev"
Requires-Dist: pytest-xdist; extra == "dev"
Requires-Dist: pyright==1.1.389; extra == "dev"
Requires-Dist: mypy==1.13.0; extra == "dev"
Requires-Dist: ruff==0.4.8; extra == "dev"
Requires-Dist: poethepoet; extra == "dev"
Requires-Dist: rich; extra == "dev"
Requires-Dist: typer; extra == "dev"
Requires-Dist: polars; extra == "dev"
Requires-Dist: pytest_mock; extra == "dev"
Requires-Dist: packaging; extra == "dev"
Requires-Dist: grpcio-tools~=1.70.0; extra == "dev"
Requires-Dist: mypy-protobuf; extra == "dev"
Requires-Dist: cookiecutter; extra == "dev"
Requires-Dist: tomli; extra == "dev"
Requires-Dist: tomli-w; extra == "dev"
Requires-Dist: chainlit; extra == "dev"
Requires-Dist: streamlit; extra == "dev"
Requires-Dist: playwright; extra == "dev"
Requires-Dist: build; extra == "dev"
Requires-Dist: twine; extra == "dev"
Dynamic: license-file
